multiassayexperiment/MultiAssayExperiment.py
multiassayexperiment/__init__.py
multiassayexperiment/io/__init__.py
multiassayexperiment/io/h5ad.py
multiassayexperiment/io/interface.py
multiassayexperiment-0.6.0.dist-info/licenses/LICENSE.txt
multiassayexperiment-0.6.0.dist-info/METADATA
multiassayexperiment-0.6.0.dist-info/WHEEL
multiassayexperiment-0.6.0.dist-info/top_level.txt
multiassayexperiment-0.6.0.dist-info/RECORD
