Metadata-Version: 2.4
Name: MultiAssayExperiment
Version: 0.6.0
Summary: Container class for representing and managing multi-omics genomic experiments
Home-page: https://github.com/BiocPy/MultiAssayExperiment
Author: jkanche
Author-email: jayaram.kancherla@gmail.com
License: MIT
Project-URL: Documentation, https://github.com/BiocPy/MultiAssayExperiment
Platform: any
Classifier: Development Status :: 4 - Beta
Classifier: Programming Language :: Python
Requires-Python: >=3.9
License-File: LICENSE.txt
Requires-Dist: importlib-metadata; python_version < "3.8"
Requires-Dist: biocframe>=0.5.6
Requires-Dist: biocutils>=0.1.4
Requires-Dist: summarizedexperiment>=0.4.5
Provides-Extra: optional
Requires-Dist: singlecellexperiment[optional]>=0.4.7; extra == "optional"
Requires-Dist: genomicranges; extra == "optional"
Requires-Dist: delayedarray; extra == "optional"
Provides-Extra: testing
Requires-Dist: setuptools; extra == "testing"
Requires-Dist: pytest; extra == "testing"
Requires-Dist: pytest-cov; extra == "testing"
Requires-Dist: pandas; extra == "testing"
Requires-Dist: singlecellexperiment[testing]>=0.4.7; extra == "testing"
Requires-Dist: genomicranges; extra == "testing"
Requires-Dist: delayedarray; extra == "testing"
Dynamic: license-file
